{
"meta":{"test_sets":[],"test_metrics":[],"learn_metrics":[{"best_value":"Min","name":"RMSE"}],"launch_mode":"Train","parameters":"","iteration_count":600,"learn_sets":["learn"],"name":"experiment"},
"iterations":[
{"learn":[3887.033654],"iteration":0,"passed_time":0.01791278598,"remaining_time":10.7297588},
{"learn":[3741.542923],"iteration":1,"passed_time":0.03417904378,"remaining_time":10.21953409},
{"learn":[3601.636218],"iteration":2,"passed_time":0.04962496885,"remaining_time":9.875368802},
{"learn":[3467.994491],"iteration":3,"passed_time":0.06498718346,"remaining_time":9.683090336},
{"learn":[3339.535366],"iteration":4,"passed_time":0.08008688381,"remaining_time":9.530339173},
{"learn":[3217.549091],"iteration":5,"passed_time":0.09473859581,"remaining_time":9.379120985},
{"learn":[3099.42038],"iteration":6,"passed_time":0.1092206286,"remaining_time":9.252547541},
{"learn":[2986.635094],"iteration":7,"passed_time":0.123070411,"remaining_time":9.107210411},
{"learn":[2878.956292],"iteration":8,"passed_time":0.1378331062,"remaining_time":9.051040643},
{"learn":[2775.021304],"iteration":9,"passed_time":0.1517260922,"remaining_time":8.951839439},
{"learn":[2677.345056],"iteration":10,"passed_time":0.1662888993,"remaining_time":8.904014698},
{"learn":[2582.684331],"iteration":11,"passed_time":0.1806495312,"remaining_time":8.851827028},
{"learn":[2491.577871],"iteration":12,"passed_time":0.1952018204,"remaining_time":8.814112968},
{"learn":[2404.096992],"iteration":13,"passed_time":0.2098162164,"remaining_time":8.782307342},
{"learn":[2319.784356],"iteration":14,"passed_time":0.2244673687,"remaining_time":8.75422738},
{"learn":[2238.533171],"iteration":15,"passed_time":0.2387473063,"remaining_time":8.714276679},
{"learn":[2161.619674],"iteration":16,"passed_time":0.2530776689,"remaining_time":8.679075351},
{"learn":[2086.032046],"iteration":17,"passed_time":0.2675517112,"remaining_time":8.650838662},
{"learn":[2015.519961],"iteration":18,"passed_time":0.2814897589,"remaining_time":8.607660522},
{"learn":[1949.290162],"iteration":19,"passed_time":0.296438069,"remaining_time":8.596704001},
{"learn":[1884.085848],"iteration":20,"passed_time":0.3115731677,"remaining_time":8.590517337},
{"learn":[1822.2021],"iteration":21,"passed_time":0.3266395378,"remaining_time":8.581711494},
{"learn":[1762.384192],"iteration":22,"passed_time":0.3414767896,"remaining_time":8.566613374},
{"learn":[1705.435579],"iteration":23,"passed_time":0.3565301303,"remaining_time":8.556723128},
{"learn":[1650.78531],"iteration":24,"passed_time":0.3702902937,"remaining_time":8.516676756},
{"learn":[1598.735582],"iteration":25,"passed_time":0.3841786204,"remaining_time":8.481481849},
{"learn":[1548.619324],"iteration":26,"passed_time":0.3982379143,"remaining_time":8.451493515},
{"learn":[1501.009066],"iteration":27,"passed_time":0.4127771793,"remaining_time":8.432448092},
{"learn":[1455.948565],"iteration":28,"passed_time":0.4273701906,"remaining_time":8.414771684},
{"learn":[1412.290677],"iteration":29,"passed_time":0.4418554995,"remaining_time":8.395254491},
{"learn":[1370.235969],"iteration":30,"passed_time":0.4562170252,"remaining_time":8.373789915},
{"learn":[1330.791517],"iteration":31,"passed_time":0.4710832626,"remaining_time":8.361727912},
{"learn":[1292.120153],"iteration":32,"passed_time":0.4852350869,"remaining_time":8.337221038},
{"learn":[1256.225171],"iteration":33,"passed_time":0.4987363275,"remaining_time":8.302492982},
{"learn":[1221.911775],"iteration":34,"passed_time":0.5127397825,"remaining_time":8.277085061},
{"learn":[1188.924052],"iteration":35,"passed_time":0.5266610949,"remaining_time":8.25102382},
{"learn":[1157.137265],"iteration":36,"passed_time":0.5410287584,"remaining_time":8.232410568},
{"learn":[1127.229157],"iteration":37,"passed_time":0.5550632019,"remaining_time":8.209092617},
{"learn":[1099.204464],"iteration":38,"passed_time":0.569413411,"remaining_time":8.190792912},
{"learn":[1071.895701],"iteration":39,"passed_time":0.5836391976,"remaining_time":8.170948766},
{"learn":[1046.21882],"iteration":40,"passed_time":0.5975509464,"remaining_time":8.14709705},
{"learn":[1021.79819],"iteration":41,"passed_time":0.6122594108,"remaining_time":8.134303601},
{"learn":[998.9858235],"iteration":42,"passed_time":0.6269432145,"remaining_time":8.121101639},
{"learn":[976.9095532],"iteration":43,"passed_time":0.6423258198,"remaining_time":8.116662632},
{"learn":[956.2252101],"iteration":44,"passed_time":0.657361736,"remaining_time":8.107461411},
{"learn":[936.4269999],"iteration":45,"passed_time":0.6716034286,"remaining_time":8.088441293},
{"learn":[917.370352],"iteration":46,"passed_time":0.6857155951,"remaining_time":8.068100512},
{"learn":[899.1996188],"iteration":47,"passed_time":0.7003617234,"remaining_time":8.054159819},
{"learn":[881.9659278],"iteration":48,"passed_time":0.7146697322,"remaining_time":8.036388213},
{"learn":[866.001592],"iteration":49,"passed_time":0.7292180065,"remaining_time":8.021398072},
{"learn":[850.6402452],"iteration":50,"passed_time":0.7443276405,"remaining_time":8.01246813},
{"learn":[835.9758758],"iteration":51,"passed_time":0.7584990313,"remaining_time":7.993412868},
{"learn":[822.2381901],"iteration":52,"passed_time":0.7732555088,"remaining_time":7.98058044},
{"learn":[809.6788453],"iteration":53,"passed_time":0.7876420303,"remaining_time":7.963936084},
{"learn":[797.1568948],"iteration":54,"passed_time":0.8019108955,"remaining_time":7.946207965},
{"learn":[785.3368773],"iteration":55,"passed_time":0.8164423301,"remaining_time":7.931154064},
{"learn":[774.2941752],"iteration":56,"passed_time":0.8311661863,"remaining_time":7.917951564},
{"learn":[764.2111032],"iteration":57,"passed_time":0.8452483831,"remaining_time":7.898700408},
{"learn":[754.6795648],"iteration":58,"passed_time":0.8603098591,"remaining_time":7.888603962},
{"learn":[745.4931851],"iteration":59,"passed_time":0.8749917849,"remaining_time":7.874926064},
{"learn":[736.8390145],"iteration":60,"passed_time":0.8892291778,"remaining_time":7.857287325},
{"learn":[728.6659406],"iteration":61,"passed_time":0.9034972343,"remaining_time":7.840024388},
{"learn":[721.2098097],"iteration":62,"passed_time":0.9176733095,"remaining_time":7.822072495},
{"learn":[713.8400558],"iteration":63,"passed_time":0.9321489299,"remaining_time":7.806747288},
{"learn":[706.6624221],"iteration":64,"passed_time":0.9475364297,"remaining_time":7.798953691},
{"learn":[700.3775101],"iteration":65,"passed_time":0.9628311092,"remaining_time":7.790178975},
{"learn":[694.1827205],"iteration":66,"passed_time":0.9768498512,"remaining_time":7.771059264},
{"learn":[688.0784032],"iteration":67,"passed_time":0.991614549,"remaining_time":7.757925589},
{"learn":[682.4351867],"iteration":68,"passed_time":1.006438846,"remaining_time":7.745203292},
{"learn":[677.111932],"iteration":69,"passed_time":1.021010902,"remaining_time":7.730511117},
{"learn":[672.1115903],"iteration":70,"passed_time":1.035259422,"remaining_time":7.713411749},
{"learn":[667.5046683],"iteration":71,"passed_time":1.049943016,"remaining_time":7.699582116},
{"learn":[663.0296496],"iteration":72,"passed_time":1.06396809,"remaining_time":7.680975118},
{"learn":[658.909262],"iteration":73,"passed_time":1.078184663,"remaining_time":7.663853143},
{"learn":[655.1092202],"iteration":74,"passed_time":1.092572902,"remaining_time":7.648010313},
{"learn":[651.328289],"iteration":75,"passed_time":1.107409994,"remaining_time":7.635300483},
{"learn":[647.8366122],"iteration":76,"passed_time":1.121280252,"remaining_time":7.615968464},
{"learn":[644.6195875],"iteration":77,"passed_time":1.135359312,"remaining_time":7.59817386},
{"learn":[641.40346],"iteration":78,"passed_time":1.150448545,"remaining_time":7.587135344},
{"learn":[638.5442687],"iteration":79,"passed_time":1.164951463,"remaining_time":7.572184513},
{"learn":[635.8831686],"iteration":80,"passed_time":1.178766697,"remaining_time":7.552838464},
{"learn":[633.2283453],"iteration":81,"passed_time":1.193850531,"remaining_time":7.541641158},
{"learn":[630.5656627],"iteration":82,"passed_time":1.207739417,"remaining_time":7.522906971},
{"learn":[628.2158905],"iteration":83,"passed_time":1.221565413,"remaining_time":7.503901821},
{"learn":[625.9429406],"iteration":84,"passed_time":1.23653285,"remaining_time":7.491934327},
{"learn":[623.7966163],"iteration":85,"passed_time":1.250927831,"remaining_time":7.476475641},
{"learn":[621.7418787],"iteration":86,"passed_time":1.265607999,"remaining_time":7.46272303},
{"learn":[619.8355303],"iteration":87,"passed_time":1.280230001,"remaining_time":7.448610915},
{"learn":[617.8921242],"iteration":88,"passed_time":1.295008862,"remaining_time":7.43538796},
{"learn":[616.1754354],"iteration":89,"passed_time":1.308812749,"remaining_time":7.416605576},
{"learn":[614.4374777],"iteration":90,"passed_time":1.322960088,"remaining_time":7.399853681},
{"learn":[612.8349116],"iteration":91,"passed_time":1.338013374,"remaining_time":7.388160804},
{"learn":[611.4089627],"iteration":92,"passed_time":1.352778152,"remaining_time":7.374822827},
{"learn":[609.9069589],"iteration":93,"passed_time":1.367452277,"remaining_time":7.360966513},
{"learn":[608.7027679],"iteration":94,"passed_time":1.381561881,"remaining_time":7.344092105},
{"learn":[607.2803375],"iteration":95,"passed_time":1.396360339,"remaining_time":7.330891779},
{"learn":[606.064085],"iteration":96,"passed_time":1.409968792,"remaining_time":7.311487654},
{"learn":[604.9592355],"iteration":97,"passed_time":1.42375923,"remaining_time":7.293134016},
{"learn":[603.8402949],"iteration":98,"passed_time":1.437354894,"remaining_time":7.273886886},
{"learn":[602.7646535],"iteration":99,"passed_time":1.451252169,"remaining_time":7.256260847},
{"learn":[601.6812597],"iteration":100,"passed_time":1.466360899,"remaining_time":7.244693948},
{"learn":[600.7094113],"iteration":101,"passed_time":1.478915237,"remaining_time":7.220586159},
{"learn":[599.79732],"iteration":102,"passed_time":1.49326278,"remaining_time":7.205355354},
{"learn":[598.8694442],"iteration":103,"passed_time":1.506645371,"remaining_time":7.18553946},
{"learn":[598.0315875],"iteration":104,"passed_time":1.519703127,"remaining_time":7.164314741},
{"learn":[597.1468452],"iteration":105,"passed_time":1.533619765,"remaining_time":7.147246828},
{"learn":[596.3454972],"iteration":106,"passed_time":1.5477876,"remaining_time":7.131395206},
{"learn":[595.5320946],"iteration":107,"passed_time":1.563079867,"remaining_time":7.120697173},
{"learn":[594.8262157],"iteration":108,"passed_time":1.577767512,"remaining_time":7.107191268},
{"learn":[594.2002616],"iteration":109,"passed_time":1.592229923,"remaining_time":7.092660565},
{"learn":[593.5370774],"iteration":110,"passed_time":1.606046115,"remaining_time":7.075284235},
{"learn":[592.8878109],"iteration":111,"passed_time":1.620350813,"remaining_time":7.06009997},
{"learn":[592.1792965],"iteration":112,"passed_time":1.634408014,"remaining_time":7.043864629},
{"learn":[591.6393181],"iteration":113,"passed_time":1.648494017,"remaining_time":7.027790282},
{"learn":[591.1065874],"iteration":114,"passed_time":1.663094649,"remaining_time":7.013920911},
{"learn":[590.6256272],"iteration":115,"passed_time":1.676082693,"remaining_time":6.993310546},
{"learn":[590.0154497],"iteration":116,"passed_time":1.690489844,"remaining_time":6.978688845},
{"learn":[589.3943762],"iteration":117,"passed_time":1.703339872,"remaining_time":6.957710324},
{"learn":[588.9108884],"iteration":118,"passed_time":1.717100859,"remaining_time":6.940550533},
{"learn":[588.4161062],"iteration":119,"passed_time":1.730953868,"remaining_time":6.92381547},
{"learn":[587.9525546],"iteration":120,"passed_time":1.745389231,"remaining_time":6.909433403},
{"learn":[587.51676],"iteration":121,"passed_time":1.759589558,"remaining_time":6.894129578},
{"learn":[587.0639624],"iteration":122,"passed_time":1.772763057,"remaining_time":6.874861611},
{"learn":[586.598958],"iteration":123,"passed_time":1.787421021,"remaining_time":6.861390371},
{"learn":[586.2449295],"iteration":124,"passed_time":1.80154354,"remaining_time":6.845865452},
{"learn":[585.8630677],"iteration":125,"passed_time":1.815390845,"remaining_time":6.829327466},
{"learn":[585.4248237],"iteration":126,"passed_time":1.829260324,"remaining_time":6.812914436},
{"learn":[585.0683401],"iteration":127,"passed_time":1.843138733,"remaining_time":6.796574077},
{"learn":[584.76846],"iteration":128,"passed_time":1.857067362,"remaining_time":6.78045525},
{"learn":[584.4458616],"iteration":129,"passed_time":1.871035534,"remaining_time":6.764513083},
{"learn":[584.1460238],"iteration":130,"passed_time":1.885678276,"remaining_time":6.751016116},
{"learn":[583.7737125],"iteration":131,"passed_time":1.899162661,"remaining_time":6.73339489},
{"learn":[583.3962265],"iteration":132,"passed_time":1.913054903,"remaining_time":6.717267969},
{"learn":[583.0853859],"iteration":133,"passed_time":1.926771474,"remaining_time":6.700563483},
{"learn":[582.7737646],"iteration":134,"passed_time":1.93929354,"remaining_time":6.679788859},
{"learn":[582.4728443],"iteration":135,"passed_time":1.953107834,"remaining_time":6.663544375},
{"learn":[582.2149839],"iteration":136,"passed_time":1.96740576,"remaining_time":6.648969831},
{"learn":[581.9818508],"iteration":137,"passed_time":1.980911635,"remaining_time":6.631747648},
{"learn":[581.722505],"iteration":138,"passed_time":1.993852155,"remaining_time":6.612703911},
{"learn":[581.4639483],"iteration":139,"passed_time":2.007955307,"remaining_time":6.597567438},
{"learn":[581.2639251],"iteration":140,"passed_time":2.021291493,"remaining_time":6.579948904},
{"learn":[581.0151889],"iteration":141,"passed_time":2.033212398,"remaining_time":6.557825902},
{"learn":[580.7746345],"iteration":142,"passed_time":2.047408309,"remaining_time":6.543116065},
{"learn":[580.533199],"iteration":143,"passed_time":2.061863744,"remaining_time":6.529235188},
{"learn":[580.2572824],"iteration":144,"passed_time":2.075010879,"remaining_time":6.511241034},
{"learn":[579.988602],"iteration":145,"passed_time":2.088367955,"remaining_time":6.493966107},
{"learn":[579.7767911],"iteration":146,"passed_time":2.101939318,"remaining_time":6.477404836},
{"learn":[579.5937912],"iteration":147,"passed_time":2.115256062,"remaining_time":6.460106351},
{"learn":[579.410875],"iteration":148,"passed_time":2.129420152,"remaining_time":6.445426096},
{"learn":[579.1602308],"iteration":149,"passed_time":2.142995769,"remaining_time":6.428987306},
{"learn":[578.9670491],"iteration":150,"passed_time":2.157363138,"remaining_time":6.41494072},
{"learn":[578.7472607],"iteration":151,"passed_time":2.170375787,"remaining_time":6.396897057},
{"learn":[578.6086967],"iteration":152,"passed_time":2.183932482,"remaining_time":6.380508624},
{"learn":[578.3970964],"iteration":153,"passed_time":2.197559023,"remaining_time":6.36435925},
{"learn":[578.2306354],"iteration":154,"passed_time":2.211533818,"remaining_time":6.349242252},
{"learn":[578.0539826],"iteration":155,"passed_time":2.225360708,"remaining_time":6.333718937},
{"learn":[577.8840226],"iteration":156,"passed_time":2.239894174,"remaining_time":6.320210951},
{"learn":[577.7025647],"iteration":157,"passed_time":2.254570682,"remaining_time":6.307090134},
{"learn":[577.5778579],"iteration":158,"passed_time":2.268261917,"remaining_time":6.291217015},
{"learn":[577.4306329],"iteration":159,"passed_time":2.281732748,"remaining_time":6.274765058},
{"learn":[577.249926],"iteration":160,"passed_time":2.295284993,"remaining_time":6.258572125},
{"learn":[576.9924458],"iteration":161,"passed_time":2.309315052,"remaining_time":6.243703659},
{"learn":[576.7579775],"iteration":162,"passed_time":2.322668373,"remaining_time":6.227031159},
{"learn":[576.6259528],"iteration":163,"passed_time":2.335731498,"remaining_time":6.20962764},
{"learn":[576.4821726],"iteration":164,"passed_time":2.349749251,"remaining_time":6.19479348},
{"learn":[576.3384573],"iteration":165,"passed_time":2.363117444,"remaining_time":6.178270908},
{"learn":[576.1740624],"iteration":166,"passed_time":2.377130308,"remaining_time":6.163457624},
{"learn":[575.9632718],"iteration":167,"passed_time":2.390747821,"remaining_time":6.147637254},
{"learn":[575.8159021],"iteration":168,"passed_time":2.404191664,"remaining_time":6.131400043},
{"learn":[575.6463826],"iteration":169,"passed_time":2.417730805,"remaining_time":6.115436742},
{"learn":[575.5554344],"iteration":170,"passed_time":2.430651104,"remaining_time":6.09794926},
{"learn":[575.3670412],"iteration":171,"passed_time":2.443513652,"remaining_time":6.080371179},
{"learn":[575.2489279],"iteration":172,"passed_time":2.457377048,"remaining_time":6.065317915},
{"learn":[575.0797862],"iteration":173,"passed_time":2.469613173,"remaining_time":6.04629432},
{"learn":[574.9092106],"iteration":174,"passed_time":2.482140902,"remaining_time":6.028056477},
{"learn":[574.8026718],"iteration":175,"passed_time":2.496000663,"remaining_time":6.013092506},
{"learn":[574.6822712],"iteration":176,"passed_time":2.509152238,"remaining_time":5.996448568},
{"learn":[574.5598767],"iteration":177,"passed_time":2.523538589,"remaining_time":5.982771262},
{"learn":[574.461797],"iteration":178,"passed_time":2.539089585,"remaining_time":5.971825225},
{"learn":[574.3812655],"iteration":179,"passed_time":2.553622852,"remaining_time":5.958453321},
{"learn":[574.2421804],"iteration":180,"passed_time":2.566751684,"remaining_time":5.941817434},
{"learn":[574.1409072],"iteration":181,"passed_time":2.580733759,"remaining_time":5.927179733},
{"learn":[574.0298402],"iteration":182,"passed_time":2.593626916,"remaining_time":5.91006789},
{"learn":[573.9042955],"iteration":183,"passed_time":2.607519467,"remaining_time":5.895261404},
{"learn":[573.7371286],"iteration":184,"passed_time":2.621663111,"remaining_time":5.88102806},
{"learn":[573.5833844],"iteration":185,"passed_time":2.635301294,"remaining_time":5.865670623},
{"learn":[573.4941598],"iteration":186,"passed_time":2.649876472,"remaining_time":5.852400977},
{"learn":[573.3042209],"iteration":187,"passed_time":2.662912763,"remaining_time":5.835744992},
{"learn":[573.236335],"iteration":188,"passed_time":2.677649864,"remaining_time":5.822825894},
{"learn":[573.0942321],"iteration":189,"passed_time":2.690826494,"remaining_time":5.806520329},
{"learn":[572.9983405],"iteration":190,"passed_time":2.704864833,"remaining_time":5.792092757},
{"learn":[572.8928365],"iteration":191,"passed_time":2.718735021,"remaining_time":5.777311919},
{"learn":[572.7855412],"iteration":192,"passed_time":2.731388472,"remaining_time":5.759974652},
{"learn":[572.7130606],"iteration":193,"passed_time":2.746107274,"remaining_time":5.747008006},
{"learn":[572.5894355],"iteration":194,"passed_time":2.759385953,"remaining_time":5.731032364},
{"learn":[572.4823405],"iteration":195,"passed_time":2.773668403,"remaining_time":5.717153238},
{"learn":[572.3950175],"iteration":196,"passed_time":2.786663688,"remaining_time":5.700636884},
{"learn":[572.3344666],"iteration":197,"passed_time":2.801368726,"remaining_time":5.687627414},
{"learn":[572.2422809],"iteration":198,"passed_time":2.814375428,"remaining_time":5.671178626},
{"learn":[572.1137356],"iteration":199,"passed_time":2.827124575,"remaining_time":5.65424915},
{"learn":[572.0282547],"iteration":200,"passed_time":2.839391424,"remaining_time":5.636403871},
{"learn":[571.9404684],"iteration":201,"passed_time":2.853927942,"remaining_time":5.623085747},
{"learn":[571.8651],"iteration":202,"passed_time":2.866982567,"remaining_time":5.606857532},
{"learn":[571.7452023],"iteration":203,"passed_time":2.880668004,"remaining_time":5.591884949},
{"learn":[571.6750274],"iteration":204,"passed_time":2.89392789,"remaining_time":5.576104959},
{"learn":[571.5853439],"iteration":205,"passed_time":2.908876166,"remaining_time":5.563578686},
{"learn":[571.496493],"iteration":206,"passed_time":2.922426603,"remaining_time":5.548375144},
{"learn":[571.4244399],"iteration":207,"passed_time":2.935829065,"remaining_time":5.532908623},
{"learn":[571.3130162],"iteration":208,"passed_time":2.948221206,"remaining_time":5.515571729},
{"learn":[571.2008439],"iteration":209,"passed_time":2.961248388,"remaining_time":5.499461292},
{"learn":[571.1321526],"iteration":210,"passed_time":2.97598848,"remaining_time":5.486538003},
{"learn":[571.0507459],"iteration":211,"passed_time":2.989825742,"remaining_time":5.471945226},
{"learn":[570.9844446],"iteration":212,"passed_time":3.004142975,"remaining_time":5.458231603},
{"learn":[570.9209264],"iteration":213,"passed_time":3.017017144,"remaining_time":5.441909428},
{"learn":[570.7763435],"iteration":214,"passed_time":3.029628145,"remaining_time":5.425148073},
{"learn":[570.7275136],"iteration":215,"passed_time":3.044442454,"remaining_time":5.41234214},
{"learn":[570.5937271],"iteration":216,"passed_time":3.058249252,"remaining_time":5.397739463},
{"learn":[570.4793525],"iteration":217,"passed_time":3.072583295,"remaining_time":5.384067976},
{"learn":[570.4113682],"iteration":218,"passed_time":3.086747735,"remaining_time":5.370095374},
{"learn":[570.3495735],"iteration":219,"passed_time":3.101335203,"remaining_time":5.356851713},
{"learn":[570.2650204],"iteration":220,"passed_time":3.114524797,"remaining_time":5.341198634},
{"learn":[570.1957268],"iteration":221,"passed_time":3.128684342,"remaining_time":5.327219285},
{"learn":[570.056789],"iteration":222,"passed_time":3.143163589,"remaining_time":5.313778802},
{"learn":[569.9607342],"iteration":223,"passed_time":3.157685774,"remaining_time":5.30040112},
{"learn":[569.7996795],"iteration":224,"passed_time":3.17073464,"remaining_time":5.284557734},
{"learn":[569.7204951],"iteration":225,"passed_time":3.183471817,"remaining_time":5.268223272},
{"learn":[569.6228143],"iteration":226,"passed_time":3.197626907,"remaining_time":5.254250381},
{"learn":[569.5152418],"iteration":227,"passed_time":3.212078087,"remaining_time":5.240758983},
{"learn":[569.4056459],"iteration":228,"passed_time":3.226223394,"remaining_time":5.226763664},
{"learn":[569.3559264],"iteration":229,"passed_time":3.239085891,"remaining_time":5.21070339},
{"learn":[569.3055652],"iteration":230,"passed_time":3.253856637,"remaining_time":5.197719043},
{"learn":[569.24946],"iteration":231,"passed_time":3.266907601,"remaining_time":5.181991367},
{"learn":[569.1830433],"iteration":232,"passed_time":3.279691412,"remaining_time":5.165865872},
{"learn":[569.1192365],"iteration":233,"passed_time":3.291985464,"remaining_time":5.149002905},
{"learn":[569.0499333],"iteration":234,"passed_time":3.305824678,"remaining_time":5.134578756},
{"learn":[569.0049313],"iteration":235,"passed_time":3.321374495,"remaining_time":5.122797951},
{"learn":[568.896654],"iteration":236,"passed_time":3.333399816,"remaining_time":5.105587059},
{"learn":[568.8181374],"iteration":237,"passed_time":3.347719945,"remaining_time":5.091910169},
{"learn":[568.6753885],"iteration":238,"passed_time":3.361785682,"remaining_time":5.077843645},
{"learn":[568.5775076],"iteration":239,"passed_time":3.37746132,"remaining_time":5.066191979},
{"learn":[568.4981704],"iteration":240,"passed_time":3.390228765,"remaining_time":5.050174799},
{"learn":[568.3678144],"iteration":241,"passed_time":3.403942184,"remaining_time":5.035583892},
{"learn":[568.324],"iteration":242,"passed_time":3.417534381,"remaining_time":5.020822116},
{"learn":[568.2353055],"iteration":243,"passed_time":3.430234112,"remaining_time":5.004767803},
{"learn":[568.1812074],"iteration":244,"passed_time":3.444190548,"remaining_time":4.990561814},
{"learn":[568.1241645],"iteration":245,"passed_time":3.458324763,"remaining_time":4.976613683},
{"learn":[567.9554351],"iteration":246,"passed_time":3.471004357,"remaining_time":4.960585175},
{"learn":[567.8991842],"iteration":247,"passed_time":3.486839217,"remaining_time":4.949062114},
{"learn":[567.8242958],"iteration":248,"passed_time":3.499977497,"remaining_time":4.933703219},
{"learn":[567.7606124],"iteration":249,"passed_time":3.513309703,"remaining_time":4.918633585},
{"learn":[567.6947941],"iteration":250,"passed_time":3.526188217,"remaining_time":4.902946963},
{"learn":[567.6015694],"iteration":251,"passed_time":3.540359009,"remaining_time":4.889067203},
{"learn":[567.5616668],"iteration":252,"passed_time":3.554495491,"remaining_time":4.875138085},
{"learn":[567.5111073],"iteration":253,"passed_time":3.567170062,"remaining_time":4.859215911},
{"learn":[567.440491],"iteration":254,"passed_time":3.579658507,"remaining_time":4.843067392},
{"learn":[567.3867889],"iteration":255,"passed_time":3.593724679,"remaining_time":4.829067537},
{"learn":[567.3199409],"iteration":256,"passed_time":3.60716141,"remaining_time":4.814227096},
{"learn":[567.1667759],"iteration":257,"passed_time":3.620011897,"remaining_time":4.798620422},
{"learn":[567.1060808],"iteration":258,"passed_time":3.633468516,"remaining_time":4.783833065},
{"learn":[567.0144557],"iteration":259,"passed_time":3.647153708,"remaining_time":4.769354849},
{"learn":[566.9410925],"iteration":260,"passed_time":3.661420861,"remaining_time":4.755638589},
{"learn":[566.8901851],"iteration":261,"passed_time":3.675780718,"remaining_time":4.742037721},
{"learn":[566.7639993],"iteration":262,"passed_time":3.690223977,"remaining_time":4.728537948},
{"learn":[566.7080692],"iteration":263,"passed_time":3.703535258,"remaining_time":4.713590328},
{"learn":[566.6431897],"iteration":264,"passed_time":3.716215377,"remaining_time":4.697857174},
{"learn":[566.5772396],"iteration":265,"passed_time":3.729987751,"remaining_time":4.683518454},
{"learn":[566.4888889],"iteration":266,"passed_time":3.743417071,"remaining_time":4.668756123},
{"learn":[566.4291036],"iteration":267,"passed_time":3.757114265,"remaining_time":4.654335582},
{"learn":[566.3509729],"iteration":268,"passed_time":3.770856125,"remaining_time":4.63997538},
{"learn":[566.2985479],"iteration":269,"passed_time":3.783703975,"remaining_time":4.62452708},
{"learn":[566.217661],"iteration":270,"passed_time":3.797716574,"remaining_time":4.610512003},
{"learn":[566.1773638],"iteration":271,"passed_time":3.812392048,"remaining_time":4.597296293},
{"learn":[566.0696353],"iteration":272,"passed_time":3.825682493,"remaining_time":4.582410898},
{"learn":[566.0159335],"iteration":273,"passed_time":3.839169765,"remaining_time":4.567771326},
{"learn":[565.9694639],"iteration":274,"passed_time":3.85257865,"remaining_time":4.553047496},
{"learn":[565.9135935],"iteration":275,"passed_time":3.866653321,"remaining_time":4.539114768},
{"learn":[565.8415905],"iteration":276,"passed_time":3.880469658,"remaining_time":4.524879781},
{"learn":[565.7736322],"iteration":277,"passed_time":3.893845901,"remaining_time":4.510138059},
{"learn":[565.7205885],"iteration":278,"passed_time":3.907538001,"remaining_time":4.495769528},
{"learn":[565.6185205],"iteration":279,"passed_time":3.919954217,"remaining_time":4.479947676},
{"learn":[565.5697547],"iteration":280,"passed_time":3.934082055,"remaining_time":4.466093151},
{"learn":[565.535948],"iteration":281,"passed_time":3.947928441,"remaining_time":4.451919306},
{"learn":[565.4767635],"iteration":282,"passed_time":3.960778559,"remaining_time":4.436631813},
{"learn":[565.3854928],"iteration":283,"passed_time":3.974461179,"remaining_time":4.422287791},
{"learn":[565.3248998],"iteration":284,"passed_time":3.988507688,"remaining_time":4.408350603},
{"learn":[565.2693081],"iteration":285,"passed_time":4.002489813,"remaining_time":4.394341963},
{"learn":[565.221654],"iteration":286,"passed_time":4.017782356,"remaining_time":4.381762639},
{"learn":[565.1619475],"iteration":287,"passed_time":4.03168074,"remaining_time":4.367654136},
{"learn":[565.058849],"iteration":288,"passed_time":4.0443769,"remaining_time":4.352253343},
{"learn":[565.0210538],"iteration":289,"passed_time":4.058297539,"remaining_time":4.338180128},
{"learn":[564.9626701],"iteration":290,"passed_time":4.071412862,"remaining_time":4.323252832},
{"learn":[564.8770133],"iteration":291,"passed_time":4.08519807,"remaining_time":4.30904454},
{"learn":[564.8055986],"iteration":292,"passed_time":4.100541882,"remaining_time":4.296472211},
{"learn":[564.7249808],"iteration":293,"passed_time":4.114662133,"remaining_time":4.282607527},
{"learn":[564.6738785],"iteration":294,"passed_time":4.12919185,"remaining_time":4.269164455},
{"learn":[564.6338927],"iteration":295,"passed_time":4.142762103,"remaining_time":4.254728647},
{"learn":[564.5627581],"iteration":296,"passed_time":4.156735409,"remaining_time":4.240709862},
{"learn":[564.5293198],"iteration":297,"passed_time":4.170739559,"remaining_time":4.22672264},
{"learn":[564.4624557],"iteration":298,"passed_time":4.184377027,"remaining_time":4.212366171},
{"learn":[564.3845469],"iteration":299,"passed_time":4.197605821,"remaining_time":4.197605821},
{"learn":[564.3128803],"iteration":300,"passed_time":4.211415811,"remaining_time":4.183432981},
{"learn":[564.2620547],"iteration":301,"passed_time":4.226321361,"remaining_time":4.170343595},
{"learn":[564.2220723],"iteration":302,"passed_time":4.238148526,"remaining_time":4.154224793},
{"learn":[564.1657806],"iteration":303,"passed_time":4.251580689,"remaining_time":4.139696986},
{"learn":[564.1143834],"iteration":304,"passed_time":4.265223546,"remaining_time":4.125380151},
{"learn":[564.081022],"iteration":305,"passed_time":4.279481405,"remaining_time":4.111658605},
{"learn":[564.0207153],"iteration":306,"passed_time":4.293682745,"remaining_time":4.097879623},
{"learn":[563.9501785],"iteration":307,"passed_time":4.309149227,"remaining_time":4.085297319},
{"learn":[563.8843317],"iteration":308,"passed_time":4.323503041,"remaining_time":4.071648495},
{"learn":[563.8295233],"iteration":309,"passed_time":4.336740629,"remaining_time":4.056950911},
{"learn":[563.7570302],"iteration":310,"passed_time":4.351616126,"remaining_time":4.04378476},
{"learn":[563.6237562],"iteration":311,"passed_time":4.365988463,"remaining_time":4.030143197},
{"learn":[563.6037294],"iteration":312,"passed_time":4.380438899,"remaining_time":4.016568575},
{"learn":[563.5435228],"iteration":313,"passed_time":4.394342218,"remaining_time":4.002490045},
{"learn":[563.4142311],"iteration":314,"passed_time":4.408286917,"remaining_time":3.988450068},
{"learn":[563.297872],"iteration":315,"passed_time":4.421671391,"remaining_time":3.9739072},
{"learn":[563.2457823],"iteration":316,"passed_time":4.436005969,"remaining_time":3.96021984},
{"learn":[563.2159842],"iteration":317,"passed_time":4.450420632,"remaining_time":3.946599428},
{"learn":[563.0894847],"iteration":318,"passed_time":4.463508742,"remaining_time":3.931805506},
{"learn":[563.0552357],"iteration":319,"passed_time":4.47715502,"remaining_time":3.917510643},
{"learn":[562.9759076],"iteration":320,"passed_time":4.491444171,"remaining_time":3.903778579},
{"learn":[562.9227678],"iteration":321,"passed_time":4.504810307,"remaining_time":3.889246166},
{"learn":[562.855876],"iteration":322,"passed_time":4.519644403,"remaining_time":3.875979875},
{"learn":[562.7842326],"iteration":323,"passed_time":4.533900943,"remaining_time":3.862211914},
{"learn":[562.7245709],"iteration":324,"passed_time":4.548711177,"remaining_time":3.848909457},
{"learn":[562.6630592],"iteration":325,"passed_time":4.56178786,"remaining_time":3.834140717},
{"learn":[562.5827521],"iteration":326,"passed_time":4.576272605,"remaining_time":3.820557863},
{"learn":[562.5234301],"iteration":327,"passed_time":4.590640164,"remaining_time":3.806872331},
{"learn":[562.4882018],"iteration":328,"passed_time":4.604356035,"remaining_time":3.792645852},
{"learn":[562.4294677],"iteration":329,"passed_time":4.618437273,"remaining_time":3.778721405},
{"learn":[562.3980211],"iteration":330,"passed_time":4.632377153,"remaining_time":3.76468113},
{"learn":[562.3521214],"iteration":331,"passed_time":4.646960481,"remaining_time":3.75116087},
{"learn":[562.3022645],"iteration":332,"passed_time":4.661641538,"remaining_time":3.737712584},
{"learn":[562.2724897],"iteration":333,"passed_time":4.676626375,"remaining_time":3.724498849},
{"learn":[562.1927045],"iteration":334,"passed_time":4.690536301,"remaining_time":3.710424238},
{"learn":[562.1045067],"iteration":335,"passed_time":4.706287724,"remaining_time":3.697797497},
{"learn":[562.0515192],"iteration":336,"passed_time":4.721068912,"remaining_time":3.684395026},
{"learn":[562.0132987],"iteration":337,"passed_time":4.735292501,"remaining_time":3.670552176},
{"learn":[561.987902],"iteration":338,"passed_time":4.748793307,"remaining_time":3.656150599},
{"learn":[561.9735773],"iteration":339,"passed_time":4.761516954,"remaining_time":3.641160024},
{"learn":[561.8972112],"iteration":340,"passed_time":4.775360404,"remaining_time":3.627033269},
{"learn":[561.8870551],"iteration":341,"passed_time":4.78945236,"remaining_time":3.61309564},
{"learn":[561.8654293],"iteration":342,"passed_time":4.803835599,"remaining_time":3.599375362},
{"learn":[561.7503032],"iteration":343,"passed_time":4.817841966,"remaining_time":3.585370766},
{"learn":[561.7084792],"iteration":344,"passed_time":4.832695599,"remaining_time":3.571992399},
{"learn":[561.6791223],"iteration":345,"passed_time":4.847781086,"remaining_time":3.558775711},
{"learn":[561.6316898],"iteration":346,"passed_time":4.861254115,"remaining_time":3.544372597},
{"learn":[561.6122784],"iteration":347,"passed_time":4.874971165,"remaining_time":3.530151533},
{"learn":[561.5794976],"iteration":348,"passed_time":4.89024359,"remaining_time":3.517051981},
{"learn":[561.5179034],"iteration":349,"passed_time":4.903244769,"remaining_time":3.502317692},
{"learn":[561.4630501],"iteration":350,"passed_time":4.917134194,"remaining_time":3.488223402},
{"learn":[561.3760251],"iteration":351,"passed_time":4.931490746,"remaining_time":3.474459389},
{"learn":[561.3500656],"iteration":352,"passed_time":4.946210352,"remaining_time":3.460946053},
{"learn":[561.2994519],"iteration":353,"passed_time":4.960326364,"remaining_time":3.447006456},
{"learn":[561.1729371],"iteration":354,"passed_time":4.973996719,"remaining_time":3.432758299},
{"learn":[561.054202],"iteration":355,"passed_time":4.988229512,"remaining_time":3.418898879},
{"learn":[561.0160855],"iteration":356,"passed_time":5.003044395,"remaining_time":3.40543358},
{"learn":[560.9839506],"iteration":357,"passed_time":5.017652533,"remaining_time":3.391820986},
{"learn":[560.9008056],"iteration":358,"passed_time":5.032123584,"remaining_time":3.378110818},
{"learn":[560.8252797],"iteration":359,"passed_time":5.046612809,"remaining_time":3.364408539},
{"learn":[560.8028035],"iteration":360,"passed_time":5.059786557,"remaining_time":3.349830989},
{"learn":[560.7485232],"iteration":361,"passed_time":5.075259066,"remaining_time":3.336772535},
{"learn":[560.6676557],"iteration":362,"passed_time":5.089619658,"remaining_time":3.322974818},
{"learn":[560.6184997],"iteration":363,"passed_time":5.104602956,"remaining_time":3.309577741},
{"learn":[560.5497831],"iteration":364,"passed_time":5.118717904,"remaining_time":3.295612897},
{"learn":[560.44949],"iteration":365,"passed_time":5.133033734,"remaining_time":3.281775666},
{"learn":[560.3371036],"iteration":366,"passed_time":5.145341499,"remaining_time":3.266660952},
{"learn":[560.2874234],"iteration":367,"passed_time":5.159088399,"remaining_time":3.252468773},
{"learn":[560.1717614],"iteration":368,"passed_time":5.173096004,"remaining_time":3.238442214},
{"learn":[560.0638427],"iteration":369,"passed_time":5.185792568,"remaining_time":3.223600786},
{"learn":[560.0398666],"iteration":370,"passed_time":5.20000141,"remaining_time":3.209704374},
{"learn":[559.980883],"iteration":371,"passed_time":5.213968833,"remaining_time":3.195658317},
{"learn":[559.9154135],"iteration":372,"passed_time":5.229025679,"remaining_time":3.182275681},
{"learn":[559.8946151],"iteration":373,"passed_time":5.243456028,"remaining_time":3.168505515},
{"learn":[559.8565537],"iteration":374,"passed_time":5.258304507,"remaining_time":3.154982704},
{"learn":[559.769079],"iteration":375,"passed_time":5.272011289,"remaining_time":3.140772683},
{"learn":[559.6612123],"iteration":376,"passed_time":5.285505803,"remaining_time":3.126439772},
{"learn":[559.5958211],"iteration":377,"passed_time":5.299772091,"remaining_time":3.112564561},
{"learn":[559.5428766],"iteration":378,"passed_time":5.313791637,"remaining_time":3.098543408},
{"learn":[559.496416],"iteration":379,"passed_time":5.328076738,"remaining_time":3.084676006},
{"learn":[559.3906095],"iteration":380,"passed_time":5.339990465,"remaining_time":3.069443338},
{"learn":[559.3294548],"iteration":381,"passed_time":5.354816091,"remaining_time":3.055889811},
{"learn":[559.2224593],"iteration":382,"passed_time":5.369513269,"remaining_time":3.042256865},
{"learn":[559.186411],"iteration":383,"passed_time":5.385383037,"remaining_time":3.029277958},
{"learn":[559.1104424],"iteration":384,"passed_time":5.398791632,"remaining_time":3.014909612},
{"learn":[559.0699141],"iteration":385,"passed_time":5.412727772,"remaining_time":3.000838713},
{"learn":[559.0632637],"iteration":386,"passed_time":5.425993831,"remaining_time":2.986399706},
{"learn":[559.0217583],"iteration":387,"passed_time":5.440139448,"remaining_time":2.972447327},
{"learn":[559.0109794],"iteration":388,"passed_time":5.452796519,"remaining_time":2.957686544},
{"learn":[558.9099728],"iteration":389,"passed_time":5.466913889,"remaining_time":2.943722863},
{"learn":[558.8386587],"iteration":390,"passed_time":5.480922623,"remaining_time":2.929700328},
{"learn":[558.7972232],"iteration":391,"passed_time":5.495678791,"remaining_time":2.91607446},
{"learn":[558.7275668],"iteration":392,"passed_time":5.508850127,"remaining_time":2.901608082},
{"learn":[558.6876812],"iteration":393,"passed_time":5.522257264,"remaining_time":2.887271565},
{"learn":[558.649236],"iteration":394,"passed_time":5.535991369,"remaining_time":2.873109445},
{"learn":[558.637614],"iteration":395,"passed_time":5.54930163,"remaining_time":2.858731143},
{"learn":[558.5813649],"iteration":396,"passed_time":5.563551483,"remaining_time":2.844838668},
{"learn":[558.5142593],"iteration":397,"passed_time":5.578107429,"remaining_time":2.83109975},
{"learn":[558.4478429],"iteration":398,"passed_time":5.592026599,"remaining_time":2.817035956},
{"learn":[558.3923627],"iteration":399,"passed_time":5.605372419,"remaining_time":2.802686209},
{"learn":[558.3348956],"iteration":400,"passed_time":5.619644271,"remaining_time":2.788801022},
{"learn":[558.2810947],"iteration":401,"passed_time":5.633966693,"remaining_time":2.774938819},
{"learn":[558.2282337],"iteration":402,"passed_time":5.647448032,"remaining_time":2.760663182},
{"learn":[558.2187681],"iteration":403,"passed_time":5.662008482,"remaining_time":2.746915006},
{"learn":[558.1817344],"iteration":404,"passed_time":5.675949516,"remaining_time":2.732864582},
{"learn":[558.1389225],"iteration":405,"passed_time":5.690790224,"remaining_time":2.71924459},
{"learn":[558.0998678],"iteration":406,"passed_time":5.706050264,"remaining_time":2.705817447},
{"learn":[558.0320391],"iteration":407,"passed_time":5.719448801,"remaining_time":2.691505318},
{"learn":[557.9738695],"iteration":408,"passed_time":5.734418311,"remaining_time":2.677931289},
{"learn":[557.9189886],"iteration":409,"passed_time":5.746624177,"remaining_time":2.663069741},
{"learn":[557.8622206],"iteration":410,"passed_time":5.760638195,"remaining_time":2.649052601},
{"learn":[557.8170968],"iteration":411,"passed_time":5.774428728,"remaining_time":2.634933497},
{"learn":[557.7880515],"iteration":412,"passed_time":5.789341165,"remaining_time":2.621323966},
{"learn":[557.7508355],"iteration":413,"passed_time":5.803367923,"remaining_time":2.607310226},
{"learn":[557.7041061],"iteration":414,"passed_time":5.81622222,"remaining_time":2.592773761},
{"learn":[557.6565189],"iteration":415,"passed_time":5.83050854,"remaining_time":2.578878777},
{"learn":[557.6454452],"iteration":416,"passed_time":5.844182321,"remaining_time":2.564713105},
{"learn":[557.5936774],"iteration":417,"passed_time":5.857364495,"remaining_time":2.550335737},
{"learn":[557.5325189],"iteration":418,"passed_time":5.871639398,"remaining_time":2.536436112},
{"learn":[557.5138604],"iteration":419,"passed_time":5.885260401,"remaining_time":2.522254458},
{"learn":[557.4489425],"iteration":420,"passed_time":5.899468714,"remaining_time":2.508325178},
{"learn":[557.3856803],"iteration":421,"passed_time":5.912756952,"remaining_time":2.494006487},
{"learn":[557.313596],"iteration":422,"passed_time":5.925431257,"remaining_time":2.479435774},
{"learn":[557.2681595],"iteration":423,"passed_time":5.939104234,"remaining_time":2.46528855},
{"learn":[557.2238471],"iteration":424,"passed_time":5.952225096,"remaining_time":2.450916216},
{"learn":[557.1789487],"iteration":425,"passed_time":5.965388661,"remaining_time":2.4365672},
{"learn":[557.1458092],"iteration":426,"passed_time":5.97938043,"remaining_time":2.422559284},
{"learn":[557.0883082],"iteration":427,"passed_time":5.993451905,"remaining_time":2.408583476},
{"learn":[557.0119602],"iteration":428,"passed_time":6.007674685,"remaining_time":2.394667532},
{"learn":[556.9363973],"iteration":429,"passed_time":6.020554068,"remaining_time":2.38021905},
{"learn":[556.8864471],"iteration":430,"passed_time":6.034337853,"remaining_time":2.366132476},
{"learn":[556.8093101],"iteration":431,"passed_time":6.04679595,"remaining_time":2.351531758},
{"learn":[556.7297535],"iteration":432,"passed_time":6.061076352,"remaining_time":2.337643766},
{"learn":[556.7117859],"iteration":433,"passed_time":6.075209239,"remaining_time":2.323697543},
{"learn":[556.6564106],"iteration":434,"passed_time":6.089639034,"remaining_time":2.309863082},
{"learn":[556.6459601],"iteration":435,"passed_time":6.103516174,"remaining_time":2.29581801},
{"learn":[556.5991007],"iteration":436,"passed_time":6.117016001,"remaining_time":2.281632971},
{"learn":[556.4954605],"iteration":437,"passed_time":6.130787416,"remaining_time":2.26755151},
{"learn":[556.4562768],"iteration":438,"passed_time":6.144398411,"remaining_time":2.253412629},
{"learn":[556.4012279],"iteration":439,"passed_time":6.157570976,"remaining_time":2.239116719},
{"learn":[556.3299664],"iteration":440,"passed_time":6.170420434,"remaining_time":2.224709408},
{"learn":[556.2774393],"iteration":441,"passed_time":6.184588345,"remaining_time":2.210780449},
{"learn":[556.2443696],"iteration":442,"passed_time":6.198187209,"remaining_time":2.19664874},
{"learn":[556.1416839],"iteration":443,"passed_time":6.212067096,"remaining_time":2.182618169},
{"learn":[556.1127188],"iteration":444,"passed_time":6.225694392,"remaining_time":2.168500294},
{"learn":[556.103863],"iteration":445,"passed_time":6.238334748,"remaining_time":2.154043837},
{"learn":[556.0682651],"iteration":446,"passed_time":6.252480749,"remaining_time":2.14011086},
{"learn":[556.0239856],"iteration":447,"passed_time":6.268551219,"remaining_time":2.126829878},
{"learn":[555.993258],"iteration":448,"passed_time":6.282723319,"remaining_time":2.112898043},
{"learn":[555.9428623],"iteration":449,"passed_time":6.295570056,"remaining_time":2.098523352},
{"learn":[555.8866682],"iteration":450,"passed_time":6.30955721,"remaining_time":2.084532205},
{"learn":[555.8459969],"iteration":451,"passed_time":6.323310597,"remaining_time":2.070464532},
{"learn":[555.777485],"iteration":452,"passed_time":6.337403071,"remaining_time":2.056508281},
{"learn":[555.7608049],"iteration":453,"passed_time":6.351617891,"remaining_time":2.042590776},
{"learn":[555.7252188],"iteration":454,"passed_time":6.365295937,"remaining_time":2.028500903},
{"learn":[555.7079854],"iteration":455,"passed_time":6.379589134,"remaining_time":2.014607095},
{"learn":[555.6555054],"iteration":456,"passed_time":6.393596779,"remaining_time":2.000622187},
{"learn":[555.610757],"iteration":457,"passed_time":6.406797935,"remaining_time":1.986387133},
{"learn":[555.6006532],"iteration":458,"passed_time":6.420819688,"remaining_time":1.972408662},
{"learn":[555.5567786],"iteration":459,"passed_time":6.436354153,"remaining_time":1.958890395},
{"learn":[555.5183434],"iteration":460,"passed_time":6.451041713,"remaining_time":1.945108022},
{"learn":[555.4882755],"iteration":461,"passed_time":6.464561197,"remaining_time":1.930972825},
{"learn":[555.4390571],"iteration":462,"passed_time":6.478498445,"remaining_time":1.916963903},
{"learn":[555.3795318],"iteration":463,"passed_time":6.493216638,"remaining_time":1.903184187},
{"learn":[555.3168068],"iteration":464,"passed_time":6.5077672,"remaining_time":1.889351768},
{"learn":[555.269492],"iteration":465,"passed_time":6.52128175,"remaining_time":1.875218357},
{"learn":[555.182903],"iteration":466,"passed_time":6.533718412,"remaining_time":1.860780618},
{"learn":[555.1191527],"iteration":467,"passed_time":6.548232382,"remaining_time":1.846937339},
{"learn":[555.0692601],"iteration":468,"passed_time":6.5627522,"remaining_time":1.833092832},
{"learn":[555.0297703],"iteration":469,"passed_time":6.577057992,"remaining_time":1.819186253},
{"learn":[555.0124244],"iteration":470,"passed_time":6.589776835,"remaining_time":1.804843337},
{"learn":[554.9879019],"iteration":471,"passed_time":6.603825082,"remaining_time":1.790867819},
{"learn":[554.9409328],"iteration":472,"passed_time":6.617123782,"remaining_time":1.776690741},
{"learn":[554.9281963],"iteration":473,"passed_time":6.631931869,"remaining_time":1.762918598},
{"learn":[554.8332222],"iteration":474,"passed_time":6.644152018,"remaining_time":1.748461057},
{"learn":[554.7700562],"iteration":475,"passed_time":6.658381051,"remaining_time":1.73453624},
{"learn":[554.7412527],"iteration":476,"passed_time":6.672500164,"remaining_time":1.720581803},
{"learn":[554.6945616],"iteration":477,"passed_time":6.687107388,"remaining_time":1.706751258},
{"learn":[554.655067],"iteration":478,"passed_time":6.701486922,"remaining_time":1.692859953},
{"learn":[554.5748224],"iteration":479,"passed_time":6.713855041,"remaining_time":1.67846376},
{"learn":[554.4762562],"iteration":480,"passed_time":6.727914375,"remaining_time":1.664494409},
{"learn":[554.4635097],"iteration":481,"passed_time":6.741427187,"remaining_time":1.650390888},
{"learn":[554.4257345],"iteration":482,"passed_time":6.754676281,"remaining_time":1.636225931},
{"learn":[554.3857233],"iteration":483,"passed_time":6.767508939,"remaining_time":1.621964952},
{"learn":[554.332751],"iteration":484,"passed_time":6.780992506,"remaining_time":1.607864202},
{"learn":[554.261495],"iteration":485,"passed_time":6.79559114,"remaining_time":1.594027551},
{"learn":[554.2458221],"iteration":486,"passed_time":6.809895833,"remaining_time":1.580119567},
{"learn":[554.202523],"iteration":487,"passed_time":6.824226845,"remaining_time":1.566215997},
{"learn":[554.1632587],"iteration":488,"passed_time":6.837862771,"remaining_time":1.552152899},
{"learn":[554.0096663],"iteration":489,"passed_time":6.849945857,"remaining_time":1.537742948},
{"learn":[553.9568738],"iteration":490,"passed_time":6.8635259,"remaining_time":1.523674792},
{"learn":[553.9028099],"iteration":491,"passed_time":6.877342636,"remaining_time":1.509660579},
{"learn":[553.8755395],"iteration":492,"passed_time":6.890970816,"remaining_time":1.495606242},
{"learn":[553.8381944],"iteration":493,"passed_time":6.904975575,"remaining_time":1.481634435},
{"learn":[553.7564024],"iteration":494,"passed_time":6.917819469,"remaining_time":1.467416251},
{"learn":[553.7085836],"iteration":495,"passed_time":6.932464529,"remaining_time":1.453581272},
{"learn":[553.6451519],"iteration":496,"passed_time":6.947210888,"remaining_time":1.439764027},
{"learn":[553.6161873],"iteration":497,"passed_time":6.961577908,"remaining_time":1.425865355},
{"learn":[553.5725263],"iteration":498,"passed_time":6.976306288,"remaining_time":1.412037946},
{"learn":[553.4806984],"iteration":499,"passed_time":6.989096397,"remaining_time":1.397819279},
{"learn":[553.4384681],"iteration":500,"passed_time":7.001254874,"remaining_time":1.383481502},
{"learn":[553.4269795],"iteration":501,"passed_time":7.016179842,"remaining_time":1.369692479},
{"learn":[553.4159622],"iteration":502,"passed_time":7.030836552,"remaining_time":1.355847208},
{"learn":[553.3587959],"iteration":503,"passed_time":7.04594316,"remaining_time":1.342084411},
{"learn":[553.3102633],"iteration":504,"passed_time":7.06116981,"remaining_time":1.328338875},
{"learn":[553.232121],"iteration":505,"passed_time":7.074030954,"remaining_time":1.314148043},
{"learn":[553.1917871],"iteration":506,"passed_time":7.088153963,"remaining_time":1.300193922},
{"learn":[553.1556777],"iteration":507,"passed_time":7.102164325,"remaining_time":1.286218736},
{"learn":[553.1417608],"iteration":508,"passed_time":7.116485898,"remaining_time":1.272299051},
{"learn":[553.1087804],"iteration":509,"passed_time":7.130418392,"remaining_time":1.258309128},
{"learn":[553.0488583],"iteration":510,"passed_time":7.144647874,"remaining_time":1.244371156},
{"learn":[552.9927042],"iteration":511,"passed_time":7.159430401,"remaining_time":1.2305271},
{"learn":[552.9555305],"iteration":512,"passed_time":7.173297263,"remaining_time":1.216524097},
{"learn":[552.9339652],"iteration":513,"passed_time":7.187451465,"remaining_time":1.2025697},
{"learn":[552.8831641],"iteration":514,"passed_time":7.201311565,"remaining_time":1.188565986},
{"learn":[552.8479117],"iteration":515,"passed_time":7.214637023,"remaining_time":1.174475794},
{"learn":[552.8034907],"iteration":516,"passed_time":7.227051083,"remaining_time":1.160242243},
{"learn":[552.7406816],"iteration":517,"passed_time":7.240537036,"remaining_time":1.1461854},
{"learn":[552.7007794],"iteration":518,"passed_time":7.253154829,"remaining_time":1.131995262},
{"learn":[552.6487452],"iteration":519,"passed_time":7.267243928,"remaining_time":1.118037527},
{"learn":[552.6206886],"iteration":520,"passed_time":7.281531491,"remaining_time":1.104109382},
{"learn":[552.5876915],"iteration":521,"passed_time":7.294225603,"remaining_time":1.089941757},
{"learn":[552.5709149],"iteration":522,"passed_time":7.30808018,"remaining_time":1.075950619},
{"learn":[552.5327483],"iteration":523,"passed_time":7.321446296,"remaining_time":1.061889157},
{"learn":[552.4708346],"iteration":524,"passed_time":7.335891332,"remaining_time":1.047984476},
{"learn":[552.4648484],"iteration":525,"passed_time":7.350237801,"remaining_time":1.034063873},
{"learn":[552.4316562],"iteration":526,"passed_time":7.362999568,"remaining_time":1.019922141},
{"learn":[552.4117178],"iteration":527,"passed_time":7.37679045,"remaining_time":1.00592597},
{"learn":[552.345916],"iteration":528,"passed_time":7.390997349,"remaining_time":0.9919864117},
{"learn":[552.3150839],"iteration":529,"passed_time":7.40582667,"remaining_time":0.9781280508},
{"learn":[552.2739129],"iteration":530,"passed_time":7.418625763,"remaining_time":0.9640022178},
{"learn":[552.2390906],"iteration":531,"passed_time":7.433345519,"remaining_time":0.9501268708},
{"learn":[552.1844151],"iteration":532,"passed_time":7.447787919,"remaining_time":0.9362134907},
{"learn":[552.1390146],"iteration":533,"passed_time":7.461481376,"remaining_time":0.9222055634},
{"learn":[552.1198032],"iteration":534,"passed_time":7.475628291,"remaining_time":0.9082539046},
{"learn":[552.1051794],"iteration":535,"passed_time":7.488419973,"remaining_time":0.8941396983},
{"learn":[552.0616157],"iteration":536,"passed_time":7.50195776,"remaining_time":0.8801179495},
{"learn":[552.0047944],"iteration":537,"passed_time":7.516318302,"remaining_time":0.8661928155},
{"learn":[551.975077],"iteration":538,"passed_time":7.530525791,"remaining_time":0.8522487444},
{"learn":[551.9281685],"iteration":539,"passed_time":7.545200884,"remaining_time":0.8383556538},
{"learn":[551.9217098],"iteration":540,"passed_time":7.559050117,"remaining_time":0.8243696061},
{"learn":[551.8893681],"iteration":541,"passed_time":7.573174379,"remaining_time":0.8104134945},
{"learn":[551.8797607],"iteration":542,"passed_time":7.587883663,"remaining_time":0.7965181745},
{"learn":[551.8607791],"iteration":543,"passed_time":7.602478492,"remaining_time":0.78260808},
{"learn":[551.8166758],"iteration":544,"passed_time":7.616153516,"remaining_time":0.7686026484},
{"learn":[551.7847884],"iteration":545,"passed_time":7.629892969,"remaining_time":0.7546047992},
{"learn":[551.7549556],"iteration":546,"passed_time":7.644421597,"remaining_time":0.7406843595},
{"learn":[551.7030475],"iteration":547,"passed_time":7.659086563,"remaining_time":0.7267746374},
{"learn":[551.6487574],"iteration":548,"passed_time":7.673230517,"remaining_time":0.7128137638},
{"learn":[551.6104893],"iteration":549,"passed_time":7.68591546,"remaining_time":0.6987195872},
{"learn":[551.5417777],"iteration":550,"passed_time":7.699866057,"remaining_time":0.6847430795},
{"learn":[551.5009917],"iteration":551,"passed_time":7.714733898,"remaining_time":0.6708464259},
{"learn":[551.4330441],"iteration":552,"passed_time":7.727553911,"remaining_time":0.6567722131},
{"learn":[551.3823893],"iteration":553,"passed_time":7.741150793,"remaining_time":0.6427670334},
{"learn":[551.3420631],"iteration":554,"passed_time":7.755196768,"remaining_time":0.6287997379},
{"learn":[551.3115744],"iteration":555,"passed_time":7.768034874,"remaining_time":0.6147365728},
{"learn":[551.2630035],"iteration":556,"passed_time":7.781000335,"remaining_time":0.6006876381},
{"learn":[551.2502245],"iteration":557,"passed_time":7.793614152,"remaining_time":0.586616119},
{"learn":[551.1786572],"iteration":558,"passed_time":7.806957066,"remaining_time":0.572603291},
{"learn":[551.1614916],"iteration":559,"passed_time":7.820382381,"remaining_time":0.5585987415},
{"learn":[551.1102618],"iteration":560,"passed_time":7.834462545,"remaining_time":0.5446417812},
{"learn":[551.0686514],"iteration":561,"passed_time":7.848318705,"remaining_time":0.5306692363},
{"learn":[551.023947],"iteration":562,"passed_time":7.861521954,"remaining_time":0.5166541959},
{"learn":[551.0053262],"iteration":563,"passed_time":7.875300551,"remaining_time":0.5026787585},
{"learn":[550.9830565],"iteration":564,"passed_time":7.88759199,"remaining_time":0.4886118932},
{"learn":[550.8717261],"iteration":565,"passed_time":7.900176982,"remaining_time":0.4745689353},
{"learn":[550.8384352],"iteration":566,"passed_time":7.912985908,"remaining_time":0.4605441534},
{"learn":[550.7890815],"iteration":567,"passed_time":7.926683531,"remaining_time":0.44657372},
{"learn":[550.7519223],"iteration":568,"passed_time":7.94040902,"remaining_time":0.4326057638},
{"learn":[550.7237356],"iteration":569,"passed_time":7.95448891,"remaining_time":0.418657311},
{"learn":[550.7147964],"iteration":570,"passed_time":7.968974998,"remaining_time":0.4047290279},
{"learn":[550.6821188],"iteration":571,"passed_time":7.981779045,"remaining_time":0.3907164567},
{"learn":[550.6498596],"iteration":572,"passed_time":7.995672765,"remaining_time":0.3767594496},
{"learn":[550.6014161],"iteration":573,"passed_time":8.008945601,"remaining_time":0.3627745394},
{"learn":[550.4853687],"iteration":574,"passed_time":8.022089086,"remaining_time":0.348786482},
{"learn":[550.4341665],"iteration":575,"passed_time":8.036478658,"remaining_time":0.3348532774},
{"learn":[550.4256464],"iteration":576,"passed_time":8.051590095,"remaining_time":0.3209472655},
{"learn":[550.4083581],"iteration":577,"passed_time":8.066809074,"remaining_time":0.3070411758},
{"learn":[550.3423286],"iteration":578,"passed_time":8.080358722,"remaining_time":0.2930700055},
{"learn":[550.3217572],"iteration":579,"passed_time":8.095193137,"remaining_time":0.2791445909},
{"learn":[550.2775103],"iteration":580,"passed_time":8.110319991,"remaining_time":0.2652256107},
{"learn":[550.2409576],"iteration":581,"passed_time":8.125845956,"remaining_time":0.2513148234},
{"learn":[550.135311],"iteration":582,"passed_time":8.140091614,"remaining_time":0.237361162},
{"learn":[550.0863626],"iteration":583,"passed_time":8.155942704,"remaining_time":0.223450485},
{"learn":[550.0527405],"iteration":584,"passed_time":8.171424417,"remaining_time":0.209523703},
{"learn":[550.018729],"iteration":585,"passed_time":8.187174522,"remaining_time":0.1955980261},
{"learn":[549.9931533],"iteration":586,"passed_time":8.20225885,"remaining_time":0.1816513885},
{"learn":[549.9516954],"iteration":587,"passed_time":8.217622988,"remaining_time":0.1677065916},
{"learn":[549.912068],"iteration":588,"passed_time":8.232852679,"remaining_time":0.1537544643},
{"learn":[549.8841235],"iteration":589,"passed_time":8.247275497,"remaining_time":0.1397843305},
{"learn":[549.8371546],"iteration":590,"passed_time":8.262293665,"remaining_time":0.1258217309},
{"learn":[549.8050317],"iteration":591,"passed_time":8.277264398,"remaining_time":0.1118549243},
{"learn":[549.7739294],"iteration":592,"passed_time":8.292205941,"remaining_time":0.09788438716},
{"learn":[549.7092256],"iteration":593,"passed_time":8.305845828,"remaining_time":0.0838974326},
{"learn":[549.6727818],"iteration":594,"passed_time":8.320280716,"remaining_time":0.06991832535},
{"learn":[549.6436929],"iteration":595,"passed_time":8.33489699,"remaining_time":0.05593890597},
{"learn":[549.55142],"iteration":596,"passed_time":8.350327288,"remaining_time":0.04196144366},
{"learn":[549.5249024],"iteration":597,"passed_time":8.366747419,"remaining_time":0.02798243284},
{"learn":[549.4878049],"iteration":598,"passed_time":8.382828421,"remaining_time":0.01399470521},
{"learn":[549.4614867],"iteration":599,"passed_time":8.398034496,"remaining_time":0}
]}